[{"id": 15004, "title": "Setting up a Docker registry cache to reduce data transfer costs", "title_zh": "\u8bbe\u7f6eDocker\u6ce8\u518c\u8868\u7f13\u5b58\u4ee5\u51cf\u5c11\u6570\u636e\u4f20\u8f93\u6210\u672c", "url": "https://lambda.grofers.com/reducing-data-transfer-costs-with-a-docker-registry-based-cache-8f93d7e561f3", "create_at": "2021-06-09 19:44", "site_name": "hacknews"}, {"id": 15003, "title": "Async Python in Real Life", "title_zh": "\u73b0\u5b9e\u751f\u6d3b\u4e2d\u7684\u5f02\u6b65Python", "url": "https://blog.guilatrova.dev/async-python-in-real-life/", "create_at": "2021-06-09 19:44", "site_name": "hacknews"}, {"id": 15002, "title": "Advancing Excel, the most successful functional programming tool, using Haskell", "title_zh": "\u63a8\u8fdbExcel\uff0c\u6700\u6210\u529f\u7684\u529f\u80fd\u7f16\u7a0b\u5de5\u5177\uff0c\u4f7f\u7528Haskell", "url": "https://www.microsoft.com/en-us/research/podcast/advancing-excel-as-a-programming-language-with-andy-gordon-and-simon-peyton-jones/", "create_at": "2021-06-09 19:29", "site_name": "hacknews"}, {"id": 15001, "title": "Propaganda Linux Desktop Backgrounds", "title_zh": "\u5ba3\u4f20Linux\u684c\u9762\u80cc\u666f", "url": "https://en.wikipedia.org/wiki/Propaganda_(desktop_backgrounds)", "create_at": "2021-06-09 19:29", "site_name": "hacknews"}, {"id": 15000, "title": "How to break out of JavaScript forEach() loop", "title_zh": "\u5982\u4f55\u7a81\u7834javascript foreach\uff08\uff09\u5faa\u73af", "url": "https://www.dottedsquirrel.com/foreach/", "create_at": "2021-06-09 19:06", "site_name": "hacknews"}, {"id": 14999, "title": "Developer Deployments on ArangoDB Oasis", "title_zh": "Arangodb Oasis\u4e0a\u7684\u5f00\u53d1\u4eba\u5458\u90e8\u7f72", "url": "https://www.arangodb.com/2021/06/introducing-developer-deployments-on-arangodb-oasis/", "create_at": "2021-06-09 19:06", "site_name": "hacknews"}, {"id": 14998, "title": "Smuggling via Windows services display name \u2013 Lateral movement", "title_zh": "\u901a\u8fc7Windows\u670d\u52a1\u663e\u793a\u540d\u79f0 - \u6a2a\u5411\u79fb\u52a8", "url": "https://0xsp.com/security%20research%20&%20development%20(SRD)/smuggling-via-windows-services-display-name-lateral-movement", "create_at": "2021-06-09 19:06", "site_name": "hacknews"}, {"id": 14997, "title": "Fractalrabbit: Simulate realistic trajectory data from sporadic reporting", "title_zh": "Fractalrabbit\uff1a\u6a21\u62df\u96f6\u661f\u62a5\u544a\u7684\u73b0\u5b9e\u8f68\u8ff9\u6570\u636e", "url": "https://github.com/NationalSecurityAgency/fractalrabbit", "create_at": "2021-06-09 19:06", "site_name": "hacknews"}, {"id": 14996, "title": "Dejavu: Game Maker Reimplementation in Rust", "title_zh": "dejavu\uff1a\u9508\u7684\u6e38\u620f\u5236\u9020\u5546\u91cd\u65b0\u5b9e\u73b0", "url": "https://github.com/rpjohnst/dejavu", "create_at": "2021-06-09 18:52", "site_name": "hacknews"}, {"id": 14995, "title": "Lua-RTOS: a real-time operating system for ESP32", "title_zh": "LUA-RTO\uff1aESP32\u7684\u5b9e\u65f6\u64cd\u4f5c\u7cfb\u7edf", "url": "https://github.com/whitecatboard/Lua-RTOS-ESP32", "create_at": "2021-06-09 18:52", "site_name": "hacknews"}, {"id": 14994, "title": "Traefik Error Pages", "title_zh": "traefik\u9519\u8bef\u9875\u9762", "url": "https://midnighter.github.io/errorpages-demo/", "create_at": "2021-06-09 18:31", "site_name": "hacknews"}, {"id": 14993, "title": "Show HN: Open-source conversational platform and unified messaging APIs", "title_zh": "\u663e\u793aHN\uff1a\u5f00\u6e90\u4f1a\u8bdd\u5e73\u53f0\u548c\u7edf\u4e00\u6d88\u606fAPI", "url": "https://airy.co/hn", "create_at": "2021-06-09 18:31", "site_name": "hacknews"}, {"id": 14992, "title": "QuestDB built a megafast time series database. Can it build a business to match?", "title_zh": "QuestDB\u6784\u5efa\u4e86Megafast\u65f6\u95f4\u5e8f\u5217\u6570\u636e\u5e93\u3002", "url": "https://www.techrepublic.com/article/questdb-has-built-a-lightning-fast-time-series-database-can-it-build-a-business-to-match/", "create_at": "2021-06-09 18:00", "site_name": "hacknews"}, {"id": 14991, "title": "Optimizing Pairing-Based Cryptography: Montgomery Arithmetic in Rust", "title_zh": "\u4f18\u5316\u57fa\u4e8e\u914d\u5bf9\u7684\u5bc6\u7801\u5b66\uff1aRust\u4e2d\u7684\u8499\u54e5\u9a6c\u5229\u7b97\u672f", "url": "https://research.nccgroup.com/2021/06/09/optimizing-pairing-based-cryptography-montgomery-arithmetic-in-rust/", "create_at": "2021-06-09 18:00", "site_name": "hacknews"}, {"id": 14990, "title": "Dasung 25.3\u201c E-ink Monitor Paperlike 253 work with Huawei Mate 20", "title_zh": "Dasung 25.3\u201c\u7535\u5b50\u58a8\u6c34\u76d1\u6d4b\u5668\u7eb8253\u4e0e\u534e\u4e3a\u4f34\u4fa3\u4e00\u8d77\u4f7f\u752820", "url": "https://www.youtube.com/watch?v=klHRJmFiavQ", "create_at": "2021-06-09 17:51", "site_name": "hacknews"}, {"id": 14989, "title": "Minimax Algorithm Guide: How to Create an Unbeatable AI", "title_zh": "minimax\u7b97\u6cd5\u6307\u5357\uff1a\u5982\u4f55\u521b\u5efa\u4e00\u4e2a\u65e0\u6cd5\u5339\u914d\u7684ai", "url": "https://www.freecodecamp.org/news/minimax-algorithm-guide-how-to-create-an-unbeatable-ai/", "create_at": "2021-06-09 17:28", "site_name": "hacknews"}, {"id": 14988, "title": "Asana Desktop for Windows and Mac", "title_zh": "asana\u684c\u9762\u9002\u7528\u4e8eWindows\u548cMac", "url": "https://asana.com/download", "create_at": "2021-06-09 17:28", "site_name": "hacknews"}, {"id": 14987, "title": "Microsoft recruiting Go compiler and tools engineers", "title_zh": "Microsoft\u62db\u8058Go\u7f16\u8bd1\u5668\u548c\u5de5\u5177\u5de5\u7a0b\u5e08", "url": "https://careers.microsoft.com/us/en/job/1038385/Senior-Software-Engineer", "create_at": "2021-06-09 17:28", "site_name": "hacknews"}, {"id": 14986, "title": "Best Webcams for Programmers, Coders, Developers", "title_zh": "\u7528\u4e8e\u7a0b\u5e8f\u5458\uff0c\u7f16\u7801\u5668\uff0c\u5f00\u53d1\u4eba\u5458\u7684\u6700\u4f73\u7f51\u7edc\u6444\u50cf\u5934", "url": "https://l.facebook.com/l.php?u=https%3A%2F%2Fcmsinstallation.blogspot.com%2F2021%2F06%2F7-best-webcams-for-programmers-coders.html&h=AT38eeq02JSOxLM4Q2PLKE9rfVsE27OaJNgydSzXIadD3Pt6tOO-J_5CmWSCodaUZpdF_dkkqeMfVC6FPeehLdmP-e0kEs1r4LSAnyOT--IplLRxUVsIJuCJAWcwklVE7WE&s=1", "create_at": "2021-06-09 17:28", "site_name": "hacknews"}, {"id": 14985, "title": "Python: What is the difference between an expression and a statement?", "title_zh": "Python\uff1a\u8868\u8fbe\u5f0f\u548c\u9648\u8ff0\u4e4b\u95f4\u6709\u4ec0\u4e48\u533a\u522b\uff1f", "url": "https://stackoverflow.com/questions/4728073/what-is-the-difference-between-an-expression-and-a-statement-in-python", "create_at": "2021-06-09 17:00", "site_name": "hacknews"}, {"id": 14984, "title": "US Senate approves $50bn boost for chip and AI technology to counter China", "title_zh": "\u7f8e\u56fd\u53c2\u8bae\u9662\u6279\u51c6\u82af\u7247\u548cAI\u6280\u672f\u768450\u4ebf\u7f8e\u5143\uff0c\u4ee5\u62b5\u5fa1\u4e2d\u56fd", "url": "https://www.theguardian.com/us-news/2021/jun/09/us-senate-approves-50bn-boost-for-computer-chip-and-ai-technology-to-counter-china", "create_at": "2021-06-09 17:00", "site_name": "hacknews"}, {"id": 14983, "title": "A Rust-embeddable Lisp, with support for interop with native Rust functions", "title_zh": "\u4e00\u79cd\u9508\u8680\u7684LISP\uff0c\u652f\u6301\u4e0e\u672c\u673a\u9508\u529f\u80fd\u4e92\u64cd\u4f5c", "url": "https://github.com/brundonsmith/rust_lisp", "create_at": "2021-06-09 16:27", "site_name": "hacknews"}, {"id": 14982, "title": "SmolCSS", "title_zh": "\u58eb\u5175", "url": "https://smolcss.dev/", "create_at": "2021-06-09 16:27", "site_name": "hacknews"}, {"id": 14981, "title": "Create unlimited 3D models with AI", "title_zh": "\u4f7f\u7528AI\u521b\u5efa\u65e0\u9650\u5236\u76843D\u6a21\u578b", "url": "https://www.varygon.com", "create_at": "2021-06-09 15:39", "site_name": "hacknews"}, {"id": 14980, "title": "FBI paid renegade developer $180k for backdoored AN0M chat app", "title_zh": "FBI\u652f\u4ed8\u53db\u5f92\u5f00\u53d1\u4eba\u5458$ 180k\u4e3a\u540e\u536bAN0M\u804a\u5929\u5e94\u7528\u7a0b\u5e8f", "url": "https://www.theregister.com/2021/06/08/fbi_trojan_shield/", "create_at": "2021-06-09 15:39", "site_name": "hacknews"}, {"id": 14979, "title": "Chrome.scripting \u2013 Chrome Developers", "title_zh": "Chrome.scripting  -  Chrome\u5f00\u53d1\u4eba\u5458", "url": "https://developer.chrome.com/blog/crx-scripting-api/", "create_at": "2021-06-09 15:07", "site_name": "hacknews"}, {"id": 14978, "title": "It Turns Out Windows Unconditionally Reserves the First 1MB of RAM", "title_zh": "\u5b83\u62d2\u7edd\u7a97\u6237\u65e0\u6761\u4ef6\u5730\u4fdd\u7559\u4e86\u524d1MB\u7684RAM", "url": "https://www.phoronix.com/scan.php?page=news_item&px=Windows-Reserves-First-1MB-RAM", "create_at": "2021-06-09 15:07", "site_name": "hacknews"}, {"id": 14977, "title": "Three Ways to Send Emails Using Python with Code Tutorials", "title_zh": "\u4f7f\u7528Python\u4e0e\u4ee3\u7801\u6559\u7a0b\u53d1\u9001\u7535\u5b50\u90ae\u4ef6\u7684\u4e09\u79cd\u65b9\u5f0f", "url": "https://www.courier.com/blog/three-ways-to-send-emails-using-python-with-code-tutorials", "create_at": "2021-06-09 15:07", "site_name": "hacknews"}, {"id": 14976, "title": "Show HN: git-index-exec. Compile or rustfmt/gofmt your staged files directly", "title_zh": "\u663e\u793aHN\uff1aGit-index-Exec\u3002", "url": "https://gist.github.com/cormacrelf/5ac5a9f949fa1d8d2d85e5e9eedcf045", "create_at": "2021-06-09 13:54", "site_name": "hacknews"}, {"id": 14975, "title": "We need a database for vectors \u2014 A vector database", "title_zh": "\u6211\u4eec\u9700\u8981\u4e00\u4e2a\u6570\u636e\u5e93\u4e3avectors  - \u77e2\u91cf\u6570\u636e\u5e93", "url": "https://www.pinecone.io/learn/vector-database/?r=2", "create_at": "2021-06-09 13:54", "site_name": "hacknews"}, {"id": 14974, "title": "Ray 1.4.0", "title_zh": "\u5c04\u7ebf1.4.0.", "url": "https://github.com/ray-project/ray/releases/tag/ray-1.4.0", "create_at": "2021-06-09 13:54", "site_name": "hacknews"}, {"id": 14973, "title": "Lockdown.exe: Block unknown apps via Windows software restriction policy", "title_zh": "lockdown.exe\uff1a\u901a\u8fc7Windows\u8f6f\u4ef6\u9650\u5236\u7b56\u7565\u963b\u6b62\u672a\u77e5\u5e94\u7528\u7a0b\u5e8f", "url": "https://www.d7xtech.com/lockdown/", "create_at": "2021-06-09 13:54", "site_name": "hacknews"}, {"id": 14972, "title": "ShowHN: ghissue, a CLI to bulk-upload GitHub issues", "title_zh": "Showhn\uff1aGhissue\uff0c\u4e00\u4e2a\u6279\u91cf\u4e0a\u4f20GitHub\u95ee\u9898\u7684CLI", "url": "https://github.com/hcgatewood/ghissue", "create_at": "2021-06-09 13:10", "site_name": "hacknews"}, {"id": 14971, "title": "Show HN: Git-index-exec. Run e.g. code formatters on your Git index", "title_zh": "\u663e\u793aHN\uff1aGit-index-Exec\u3002", "url": "https://gist.github.com/cormacrelf/5ac5a9f949fa1d8d2d85e5e9eedcf045", "create_at": "2021-06-09 13:10", "site_name": "hacknews"}, {"id": 14970, "title": "Show HN: A simple JavaScript notebook in one file", "title_zh": "\u663e\u793aHN\uff1a\u4e00\u4e2a\u6587\u4ef6\u4e2d\u7684\u7b80\u5355JavaScript\u7b14\u8bb0\u672c", "url": "https://github.com/timcwinkler/javascript-notebook", "create_at": "2021-06-09 13:10", "site_name": "hacknews"}, {"id": 14969, "title": "Been in embedded for 20 years, and SQL sucks", "title_zh": "\u5d4c\u5165\u4e8620\u5e74\uff0cSQL\u7cdf\u900f\u4e86", "url": "item?id=27444089", "create_at": "2021-06-09 12:18", "site_name": "hacknews"}, {"id": 14968, "title": "Stationary Low-Power Reactor Number One", "title_zh": "\u9759\u6b62\u7684\u4f4e\u529f\u7387\u53cd\u5e94\u5806\u7b2c\u4e00", "url": "https://en.wikipedia.org/wiki/SL-1", "create_at": "2021-06-09 12:18", "site_name": "hacknews"}, {"id": 14967, "title": "QuestDB is the fastest open source time series database", "title_zh": "QuestDB\u662f\u6700\u5feb\u7684\u5f00\u6e90\u65f6\u95f4\u5e8f\u5217\u6570\u636e\u5e93", "url": "https://questdb.io/", "create_at": "2021-06-09 11:25", "site_name": "hacknews"}, {"id": 14966, "title": "Sane-airscan \u2013 driverless scanning with eSCL (Apple AirScan) and WSD", "title_zh": "Sane-Airscan  - \u7528ESCL\uff08Apple Airscan\uff09\u548cWSD\u65e0\u4eba\u9a7e\u9a76\u626b\u63cf", "url": "https://github.com/alexpevzner/sane-airscan", "create_at": "2021-06-09 11:25", "site_name": "hacknews"}, {"id": 14965, "title": "\u201cWhy Are Developers Only Building Luxury Housing?\u201d (2018)", "title_zh": "\u201c\u4e3a\u4ec0\u4e48\u5f00\u53d1\u5546\u53ea\u80fd\u5efa\u9020\u8c6a\u534e\u4f4f\u623f\uff1f\u201d ", "url": "https://www.strongtowns.org/journal/2018/7/25/why-are-developers-only-building-luxury-housing", "create_at": "2021-06-09 10:44", "site_name": "hacknews"}, {"id": 14964, "title": "QuestDB is the fastest open source time series database", "title_zh": "QuestDB\u662f\u6700\u5feb\u7684\u5f00\u6e90\u65f6\u95f4\u5e8f\u5217\u6570\u636e\u5e93", "url": "https://questdb.io/time-series-benchmark-suite/", "create_at": "2021-06-09 10:44", "site_name": "hacknews"}, {"id": 14963, "title": "GPT-J-6B, a 6B Parameter Text Generation Model", "title_zh": "GPT-J-6B\uff0c6B\u53c2\u6570\u6587\u672c\u751f\u6210\u6a21\u578b", "url": "https://github.com/kingoflolz/mesh-transformer-jax", "create_at": "2021-06-09 10:44", "site_name": "hacknews"}, {"id": 14962, "title": "Open Source Survival: A Story from the Trenches", "title_zh": "\u5f00\u6e90\u751f\u5b58\uff1a\u6c9f\u6e20\u7684\u6545\u4e8b", "url": "https://entreprenerd.lowagie.com/ossurvival/", "create_at": "2021-06-09 10:44", "site_name": "hacknews"}, {"id": 14961, "title": "Modify HTTP request headers with transform rules", "title_zh": "\u4f7f\u7528\u8f6c\u6362\u89c4\u5219\u4fee\u6539HTTP\u8bf7\u6c42\u6807\u5934", "url": "https://blog.cloudflare.com/transform-http-request-headers/", "create_at": "2021-06-09 09:46", "site_name": "hacknews"}, {"id": 14960, "title": "First impressions of Rust programming on Solana", "title_zh": "Solana\u4e0a\u751f\u9508\u7f16\u7a0b\u7684\u7b2c\u4e00\u5370\u8c61", "url": "https://brson.github.io/2021/06/08/rust-on-solana", "create_at": "2021-06-09 09:46", "site_name": "hacknews"}, {"id": 14959, "title": "Linux Fu: Databases Are Next-Level File Systems", "title_zh": "Linux fu\uff1a\u6570\u636e\u5e93\u662f\u4e0b\u4e00\u4e2a\u7ea7\u522b\u6587\u4ef6\u7cfb\u7edf", "url": "https://hackaday.com/2021/06/08/linux-fu-databases-are-next-level-file-systems/", "create_at": "2021-06-09 09:46", "site_name": "hacknews"}, {"id": 14958, "title": "Blocking Content with Your Safari Web Extension", "title_zh": "\u901a\u8fc7Safari Web\u6269\u5c55\u963b\u6b62\u5185\u5bb9", "url": "https://developer.apple.com/documentation/safariservices/safari_web_extensions/blocking_content_with_your_safari_web_extension", "create_at": "2021-06-09 09:46", "site_name": "hacknews"}, {"id": 14957, "title": "Haskell Is Diverse", "title_zh": "Haskell\u662f\u591a\u6837\u7684", "url": "https://tonyday567.github.io/posts/diversity/", "create_at": "2021-06-09 09:46", "site_name": "hacknews"}, {"id": 14956, "title": "Show HN: Show descendant count on Hacker News 'more' links", "title_zh": "\u663e\u793aHN\uff1a\u663e\u793a\u9ed1\u5ba2\u65b0\u95fb\u201c\u66f4\u591a\u201d\u94fe\u63a5\u7684\u540e\u4ee3\u8ba1\u6570", "url": "https://gist.github.com/shawwn/3c1b71d69482afde15efb163925f2c7a", "create_at": "2021-06-09 08:11", "site_name": "hacknews"}, {"id": 14955, "title": "How to write JavaScript code outside the browser", "title_zh": "\u5982\u4f55\u5728\u6d4f\u89c8\u5668\u5916\u7f16\u5199JavaScript\u4ee3\u7801", "url": "https://blog.genztech.xyz/writing-javascript-outside-the-browser", "create_at": "2021-06-09 08:11", "site_name": "hacknews"}, {"id": 14954, "title": "Carp", "title_zh": "\u9ca4\u9c7c", "url": "https://github.com/carp-lang/Carp", "create_at": "2021-06-09 07:50", "site_name": "hacknews"}, {"id": 14953, "title": "Apple M1 support for TensorFlow 2.5 pluggable device API", "title_zh": "Apple M1\u652f\u6301TensoRFlow 2.5\u53ef\u63d2\u62d4\u8bbe\u5907API", "url": "https://developer.apple.com/metal/tensorflow-plugin/", "create_at": "2021-06-09 07:50", "site_name": "hacknews"}, {"id": 14952, "title": "US Senate passes 750B industrial policy targeting semiconductor, AI, etc.", "title_zh": "\u7f8e\u56fd\u53c2\u8bae\u9662\u901a\u8fc7\u4e86750\u4ebf\u4e2a\u5de5\u4e1a\u653f\u7b56\uff0c\u7784\u51c6\u534a\u5bfc\u4f53\uff0cai\u7b49\u3002", "url": "https://www.nytimes.com/2021/06/07/us/politics/senate-china-semiconductors.html", "create_at": "2021-06-09 07:29", "site_name": "hacknews"}, {"id": 14951, "title": "Discover and Prevent Linux Kernel Zero-Day Exploit Using Formal Verification", "title_zh": "\u53d1\u73b0\u548c\u9632\u6b62\u4f7f\u7528\u6b63\u5f0f\u9a8c\u8bc1\u7684Linux\u5185\u6838\u96f6\u65e5\u5229\u7528", "url": "http://digamma.ai/blog/discover-prevent-linux-kernel-zero-day-exploit-using-formal-verification/", "create_at": "2021-06-09 07:29", "site_name": "hacknews"}, {"id": 14950, "title": "Do you need an open source alternative to SurveyMonkey / Typeform?", "title_zh": "\u60a8\u9700\u8981\u4e00\u4e2a\u5f00\u6e90\u66ff\u4ee3\u7684\u66ff\u4ee3\u8bfe\u7a0b\u5417\uff1f", "url": "item?id=27442362", "create_at": "2021-06-09 07:29", "site_name": "hacknews"}, {"id": 14949, "title": "46brooklyn Drug Pricing (Nadac) Dashboard", "title_zh": "46Brooklyn\u836f\u54c1\u5b9a\u4ef7\uff08Nadac\uff09\u4eea\u8868\u677f", "url": "https://www.46brooklyn.com/nadac", "create_at": "2021-06-09 06:50", "site_name": "hacknews"}, {"id": 14948, "title": "Show HN: A simple Python 3 library to read your Things app data", "title_zh": "\u663e\u793aHN\uff1a\u7b80\u5355\u7684Python 3\u5e93\uff0c\u4ee5\u9605\u8bfb\u60a8\u7684\u5e94\u7528\u7a0b\u5e8f\u6570\u636e", "url": "https://github.com/thingsapi/things.py", "create_at": "2021-06-09 06:50", "site_name": "hacknews"}, {"id": 14947, "title": "Introducing chrome.scripting", "title_zh": "\u4ecb\u7ecdChrome.Scripting.", "url": "https://developer.chrome.com/en/blog/crx-scripting-api/", "create_at": "2021-06-09 06:50", "site_name": "hacknews"}, {"id": 14946, "title": "Show HN: Best Alternative to Google dictionary extension for Firefox", "title_zh": "\u663e\u793aHN\uff1aFirefox\u7684Google Dictionary\u6269\u5c55\u540d\u7684\u6700\u4f73\u66ff\u4ee3\u65b9\u6848", "url": "https://addons.mozilla.org/en-US/firefox/addon/dictionary/", "create_at": "2021-06-09 06:50", "site_name": "hacknews"}, {"id": 14945, "title": "Pypa/pip #8187: Parallelizing the Pip install process", "title_zh": "PYPA / PIP\uff038187\uff1a\u5e76\u884c\u5316PIP\u5b89\u88c5\u8fc7\u7a0b", "url": "https://github.com/pypa/pip/issues/8187", "create_at": "2021-06-09 06:25", "site_name": "hacknews"}, {"id": 14944, "title": "Show HN: SnackUI, write-once React Native and Web UIs that compile to atomic CSS", "title_zh": "\u663e\u793aHN\uff1aSnackui\uff0c\u5199\u5165\u54cd\u5e94\u539f\u751f\u548cWeb UIS\u7f16\u8bd1\u4e3a\u539f\u5b50CSS", "url": "https://github.com/snackui/snackui", "create_at": "2021-06-09 06:25", "site_name": "hacknews"}, {"id": 14943, "title": "Rust for Fsharpers and F# for Rustaceans", "title_zh": "fsharpers\u548cf\uff03for rustaceans", "url": "https://github.com/Dhghomon/rust-fsharp", "create_at": "2021-06-09 05:56", "site_name": "hacknews"}, {"id": 14942, "title": "Rust from a JavaScript perspective \u2013 A tongue in cheek walk-through", "title_zh": "\u4ecejavascript\u900f\u89c6\u7684\u9508 - \u988a\u7a7f\u7684\u820c\u5934", "url": "https://blogs.harvard.edu/kapolos/rust-from-a-javascript-perspective/", "create_at": "2021-06-09 05:56", "site_name": "hacknews"}, {"id": 14941, "title": "How to Setup Replicated Highly Available SQLite with Rqlite", "title_zh": "\u5982\u4f55\u4f7f\u7528RQLite\u590d\u5236\u9ad8\u53ef\u7528\u6027\u7684SQLite", "url": "https://lowendbox.com/blog/how-to-setup-replicated-highly-available-sqlite-with-rqlite/", "create_at": "2021-06-09 05:39", "site_name": "hacknews"}, {"id": 14940, "title": "Explainability Won\u2019t Save AI", "title_zh": "\u89e3\u91ca\u6027\u4e0d\u4f1a\u4fdd\u5b58ai", "url": "https://www.brookings.edu/techstream/explainability-wont-save-ai/", "create_at": "2021-06-09 05:39", "site_name": "hacknews"}, {"id": 14939, "title": "Ask HN: APIs for getting books and author data", "title_zh": "\u95eeHN\uff1a\u7528\u4e8e\u83b7\u53d6\u4e66\u7c4d\u548c\u4f5c\u8005\u6570\u636e\u7684API", "url": "item?id=27441167", "create_at": "2021-06-09 05:39", "site_name": "hacknews"}, {"id": 14938, "title": "Study shows how taking short breaks may help our brains learn new skills", "title_zh": "\u7814\u7a76\u8868\u660e\uff0c\u4f11\u606f\u77ed\u6682\u53ef\u80fd\u6709\u52a9\u4e8e\u6211\u4eec\u7684\u5927\u8111\u5b66\u4e60\u65b0\u6280\u80fd", "url": "https://www.ninds.nih.gov/News-Events/News-and-Press-Releases/Press-Releases/Study-shows-how-taking-short-breaks-may-help-our-brains", "create_at": "2021-06-09 05:39", "site_name": "hacknews"}, {"id": 14937, "title": "Tsup: Bundle your TypeScript library with no config", "title_zh": "TSUP\uff1a\u6346\u7ed1\u65e0\u914d\u7f6e\u7684\u7248\u672c\u7b7e\u5b57\u5e93", "url": "https://tsup.egoist.sh/", "create_at": "2021-06-09 05:20", "site_name": "hacknews"}, {"id": 14936, "title": "Signing HTTP Messages (IETF Draft)", "title_zh": "\u7b7e\u7f72HTTP\u6d88\u606f\uff08IETF\u8349\u6848\uff09", "url": "https://www.ietf.org/archive/id/draft-ietf-httpbis-message-signatures-05.html", "create_at": "2021-06-09 05:20", "site_name": "hacknews"}, {"id": 14935, "title": "XOR Operator in Java", "title_zh": "Java\u4e2d\u7684XOR\u8fd0\u7b97\u7b26", "url": "https://jlelse.blog/dev/xor-java", "create_at": "2021-06-09 05:20", "site_name": "hacknews"}, {"id": 14934, "title": "Ppl: The command line address book", "title_zh": "PPL\uff1a\u547d\u4ee4\u884c\u5730\u5740\u7c3f", "url": "https://github.com/hendotcat/ppl", "create_at": "2021-06-09 04:55", "site_name": "hacknews"}, {"id": 14933, "title": "Astro: Ship Less JavaScript", "title_zh": "Astro\uff1a\u8239\u8236\u51cf\u5c11JavaScript", "url": "https://astro.build/blog/introducing-astro", "create_at": "2021-06-09 04:55", "site_name": "hacknews"}, {"id": 14932, "title": "Ask HN: What is the best tool to infer data type of tabular data?", "title_zh": "\u8be2\u95eeHN\uff1a\u4ec0\u4e48\u662f\u63a8\u65ad\u6570\u636e\u7c7b\u578b\u7684\u8868\u683c\u6570\u636e\u7684\u6700\u4f73\u5de5\u5177\uff1f", "url": "item?id=27440629", "create_at": "2021-06-09 04:55", "site_name": "hacknews"}, {"id": 14931, "title": "The New Vector Database [audio]", "title_zh": "\u65b0\u7684\u77e2\u91cf\u6570\u636e\u5e93[\u97f3\u9891]", "url": "https://cloudwars.co/cloud-database/pinecone-systems-ceo-edo-liberty-cloud-database-report-podcast/", "create_at": "2021-06-09 04:35", "site_name": "hacknews"}, {"id": 14930, "title": "Text Classification by Data Compression", "title_zh": "\u901a\u8fc7\u6570\u636e\u538b\u7f29\u8fdb\u884c\u6587\u672c\u5206\u7c7b", "url": "https://maxhalford.github.io/blog/text-classification-by-compression/", "create_at": "2021-06-09 04:35", "site_name": "hacknews"}, {"id": 14929, "title": "Apache Calcite 1.27.0 Released", "title_zh": "Apache Calcite 1.27.0\u53d1\u5e03", "url": "http://mail-archives.apache.org/mod_mbox/www-announce/202106.mbox/%3Cpony-561a525a90056b3dfda1b9bf4dc5b87fc305af9f-be7fbcc94b1bb4ef25e5de75bb6a2b6bce89d4c2%40announce.apache.org%3E", "create_at": "2021-06-09 04:35", "site_name": "hacknews"}, {"id": 14928, "title": "How a Raspberry Pi made it difficult for one astronaut to get to sleep on ISS", "title_zh": "\u8986\u76c6\u5b50PI\u5982\u4f55\u8ba9\u4e00\u4e2a\u5b87\u822a\u5458\u96be\u4ee5\u5165\u7761", "url": "https://www.zdnet.com/article/how-a-raspberry-pi-made-it-difficult-for-one-astronaut-to-get-to-sleep-on-the-iss/", "create_at": "2021-06-09 04:35", "site_name": "hacknews"}, {"id": 14927, "title": "React 18 Alpha is out Now what?", "title_zh": "\u53cd\u5e9418 alpha\u73b0\u5728\u51fa\u6765\u4e86\u4ec0\u4e48\uff1f", "url": "https://www.netlify.com/blog/2021/06/08/react-18-alpha-is-out-now-what/", "create_at": "2021-06-09 04:04", "site_name": "hacknews"}, {"id": 14926, "title": "Apache Superset 1.1", "title_zh": "Apache Superset 1.1", "url": "https://github.com/apache/superset/tree/master/RELEASING/release-notes-1-1", "create_at": "2021-06-09 04:04", "site_name": "hacknews"}, {"id": 14925, "title": "WinFsp 2021 \u2013 FUSE for Windows", "title_zh": "WinFSP 2021  - \u9002\u7528\u4e8eWindows\u7684\u4fdd\u9669\u4e1d", "url": "https://github.com/billziss-gh/winfsp/releases/tag/v1.9", "create_at": "2021-06-09 04:04", "site_name": "hacknews"}, {"id": 14924, "title": "A better vi mode plugin for ZSH", "title_zh": "zsh\u66f4\u597d\u7684vi\u6a21\u5f0f\u63d2\u4ef6", "url": "https://github.com/jeffreytse/zsh-vi-mode", "create_at": "2021-06-09 03:43", "site_name": "hacknews"}, {"id": 14923, "title": "Changes to the Android Search Engine \u201cChoice Screen\u201d in Europe", "title_zh": "\u6b27\u6d32\u7684Android\u641c\u7d22\u5f15\u64ce\u201c\u9009\u62e9\u5c4f\u5e55\u201d\u7684\u66f4\u6539", "url": "https://blog.google/around-the-globe/google-europe/changes-android-choice-screen-europe/", "create_at": "2021-06-09 03:43", "site_name": "hacknews"}, {"id": 14922, "title": "Show HN: Open-source A/B testing platform", "title_zh": "\u663e\u793aHN\uff1a\u5f00\u6e90A / B\u6d4b\u8bd5\u5e73\u53f0", "url": "https://github.com/growthbook/growthbook", "create_at": "2021-06-09 03:43", "site_name": "hacknews"}, {"id": 14921, "title": "Ask HN: Go vs. Rust Dependency Management", "title_zh": "\u8be2\u95eeHN\uff1aGo\u4e0eRust\u4f9d\u8d56\u7ba1\u7406", "url": "item?id=27439681", "create_at": "2021-06-09 03:43", "site_name": "hacknews"}, {"id": 14920, "title": "Show HN: daftpunk.cafe", "title_zh": "\u663e\u793aHN\uff1aDaftpunk.Cafe", "url": "https://daftpunk.cafe", "create_at": "2021-06-09 02:59", "site_name": "hacknews"}, {"id": 14919, "title": "Machine Learning Literacy for Developers", "title_zh": "\u5f00\u53d1\u4eba\u5458\u7684\u673a\u5668\u5b66\u4e60\u7d20\u517b", "url": "https://divu.in/machine-learning-literacy", "create_at": "2021-06-09 02:59", "site_name": "hacknews"}, {"id": 14918, "title": "iOS 15 Includes Secure Paste Feature That Hides the Clipboard from Developers", "title_zh": "iOS 15\u5305\u62ec\u9690\u85cf\u5f00\u53d1\u4eba\u5458\u7684\u526a\u8d34\u677f\u7684\u5b89\u5168\u7c98\u8d34\u529f\u80fd", "url": "https://www.macrumors.com/2021/06/08/ios-15-secure-paste/", "create_at": "2021-06-09 02:59", "site_name": "hacknews"}, {"id": 14917, "title": "Translating Quake 3 into Rust", "title_zh": "\u5c06Quake 3\u8f6c\u6362\u4e3a\u9508", "url": "https://immunant.com/blog/2020/01/quake3/", "create_at": "2021-06-09 02:59", "site_name": "hacknews"}, {"id": 14916, "title": "The relative performance of C and Rust (2018)", "title_zh": "C\u548cRUTR\u7684\u76f8\u5bf9\u8868\u73b0\uff082018\uff09", "url": "http://dtrace.org/blogs/bmc/2018/09/28/the-relative-performance-of-c-and-rust/", "create_at": "2021-06-09 02:59", "site_name": "hacknews"}, {"id": 14915, "title": "Rust/C++ interop in the Android Platform", "title_zh": "Android\u5e73\u53f0\u4e2d\u7684Rust / C ++\u4e92\u64cd\u4f5c", "url": "https://security.googleblog.com/2021/06/rustc-interop-in-android-platform.html", "create_at": "2021-06-09 02:02", "site_name": "hacknews"}, {"id": 14914, "title": "The Plan for React 18", "title_zh": "\u53cd\u5e9418\u7684\u8ba1\u5212", "url": "https://reactjs.org/blog/2021/06/08/the-plan-for-react-18.html", "create_at": "2021-06-09 02:02", "site_name": "hacknews"}, {"id": 14913, "title": "Linux Foundation Readies Global Covid Vaccine Certificate Network", "title_zh": "Linux\u57fa\u91d1\u4f1a\u9605\u8bfb\u5168\u7403Covid\u75ab\u82d7\u8bc1\u4e66\u7f51\u7edc", "url": "https://www.zdnet.com/article/linux-foundation-readies-global-covid-certificate-network/", "create_at": "2021-06-09 02:02", "site_name": "hacknews"}, {"id": 14912, "title": "Show HN: Convert Google Docs to Simple Markdown or HTML", "title_zh": "\u663e\u793aHN\uff1a\u5c06Google\u6587\u6863\u8f6c\u6362\u4e3a\u7b80\u5355\u7684Markdown\u6216HTML", "url": "https://gsuite.google.com/marketplace/app/docs_to_markdown/700168918607", "create_at": "2021-06-09 02:02", "site_name": "hacknews"}, {"id": 14911, "title": "New Suspense SSR Architecture in React 18", "title_zh": "\u65b0\u7684\u60ac\u7591SSR\u67b6\u6784\u5728\u53cd\u5e9418\u4e2d", "url": "https://github.com/reactwg/react-18/discussions/37", "create_at": "2021-06-09 02:02", "site_name": "hacknews"}, {"id": 14910, "title": "UDP Based F1 Game Telemetry Client with Go+sample App with Prometheus+grafana", "title_zh": "\u57fa\u4e8eUDP\u7684F1\u6e38\u620f\u9065\u6d4b\u5ba2\u6237\u7aef\u5e26Go + Sample\u5e94\u7528\u7a0b\u5e8f\uff0c\u5e26\u6709Prometheus + Grafana", "url": "https://github.com/anilmisirlioglu/f1-telemetry-go", "create_at": "2021-06-09 02:02", "site_name": "hacknews"}, {"id": 14909, "title": "What's Coming in React 18", "title_zh": "\u4ec0\u4e48\u662f\u53cd\u5e9418", "url": "https://twitter.com/reactjs/status/1402320383932502021", "create_at": "2021-06-09 02:02", "site_name": "hacknews"}, {"id": 14908, "title": "Low Latency and High Throughput in the Linux Storage Stack", "title_zh": "Linux\u5b58\u50a8\u5806\u6808\u4e2d\u7684\u4f4e\u5ef6\u8fdf\u548c\u9ad8\u541e\u5410\u91cf", "url": "https://www.youtube.com/watch?v=yue9nQRnTrU", "create_at": "2021-06-09 00:59", "site_name": "hacknews"}, {"id": 14907, "title": "Cascade: A modern library for creating user interfaces", "title_zh": "Cascade\uff1a\u521b\u5efa\u7528\u6237\u754c\u9762\u7684\u73b0\u4ee3\u5e93", "url": "https://sjohnsonaz.github.io/cascade/", "create_at": "2021-06-09 00:59", "site_name": "hacknews"}, {"id": 14906, "title": "SnowFS \u2013 a fast, scalable version control file storage for graphic files", "title_zh": "Snowfs  - \u56fe\u5f62\u6587\u4ef6\u7684\u5feb\u901f\uff0c\u53ef\u6269\u5c55\u7684\u7248\u672c\u63a7\u5236\u6587\u4ef6\u5b58\u50a8", "url": "https://github.com/snowtrack/snowfs", "create_at": "2021-06-09 00:59", "site_name": "hacknews"}, {"id": 14905, "title": "Traditionally Web Host-Focused CloudLinux Rolls Out TuxCare, an Enterprise Brand", "title_zh": "\u4f20\u7edf\u4e0a\uff0cWeb\u4e3b\u6301\u4eba\u805a\u7126\u7684CloudLinux\u63a8\u51fa\u4e86\u4f01\u4e1a\u54c1\u724c\u7684TUXCARE", "url": "https://www.datacenterknowledge.com/open-source/traditionally-web-host-focused-cloudlinux-rolls-out-tuxcare-enterprise-brand", "create_at": "2021-06-09 00:59", "site_name": "hacknews"}]