[{"id": 19795, "hacknewsid": 29593955, "title": "React Conf 2021 Recap", "title_zh": "", "url": "https://reactjs.org/blog/2021/12/17/react-conf-2021-recap.html", "create_at": "2021-12-18 00:24", "site_name": "hacknews"}, {"id": 19796, "hacknewsid": 29593869, "title": "How to avoid layout shifts caused by web fonts", "title_zh": "", "url": "https://simonhearne.com/2021/layout-shifts-webfonts/", "create_at": "2021-12-18 00:24", "site_name": "hacknews"}, {"id": 19797, "hacknewsid": 29593822, "title": "I wrote my own Go HTTP client", "title_zh": "", "url": "https://blog.carlmjohnson.net/post/2021/requests-golang-http-client/", "create_at": "2021-12-18 00:24", "site_name": "hacknews"}, {"id": 19798, "hacknewsid": 29593801, "title": "Flu vaccines don't match the main circulating flu virus strain, researchers find", "title_zh": "", "url": "https://lite.cnn.com/en/article/h_c63d00a5708a7e43ece7ee9bae16ab82", "create_at": "2021-12-18 00:24", "site_name": "hacknews"}, {"id": 19799, "hacknewsid": 29593632, "title": "Top New No-Code Tools 2021", "title_zh": "", "url": "https://www.whalesync.com//blog/top-10-new-no-code-tools-2021", "create_at": "2021-12-18 00:24", "site_name": "hacknews"}, {"id": 19800, "hacknewsid": 29593584, "title": "ReactOS 0.4.14 Released", "title_zh": "", "url": "https://reactos.org/project-news/reactos-0414-released/", "create_at": "2021-12-18 00:24", "site_name": "hacknews"}, {"id": 19801, "hacknewsid": 29593341, "title": "Fuite: a tool for finding memory leaks in web apps", "title_zh": "", "url": "https://nolanlawson.com/2021/12/17/introducing-fuite-a-tool-for-finding-memory-leaks-in-web-apps/", "create_at": "2021-12-18 00:24", "site_name": "hacknews"}, {"id": 19802, "hacknewsid": 29593331, "title": "Rust as a Platform for IoT", "title_zh": "", "url": "https://blog.ysndr.de/posts/essays/2021-12-12-rust-for-iot/", "create_at": "2021-12-18 00:24", "site_name": "hacknews"}]