[{"id": 23219, "title": "Show HN: RxEffects- reactive state and effect management with RxJS", "title_zh": "\u663e\u793aHN\uff1arxeffects-\u53cd\u5e94\u72b6\u6001\u548crxjs\u7684\u6548\u679c\u7ba1\u7406", "url": "https://github.com/mnasyrov/rx-effects", "create_at": "2021-08-15 00:52", "site_name": "hacknews"}, {"id": 23218, "title": "Show HN: SQLite-S3-query \u2013 Python function to query a SQLite database on S3", "title_zh": "\u663e\u793aHN\uff1aSQLite-S3\u67e5\u8be2 -  Python\u51fd\u6570\u5728S3\u4e0a\u67e5\u8be2SQLite\u6570\u636e\u5e93", "url": "https://github.com/michalc/sqlite-s3-query", "create_at": "2021-08-15 00:52", "site_name": "hacknews"}, {"id": 23217, "title": "Ask HN: I am a web dev who wants to build a mobile MVP", "title_zh": "\u95eeHN\uff1a\u6211\u662f\u4e00\u4e2a\u60f3\u8981\u6784\u5efa\u79fb\u52a8MVP\u7684\u7f51\u7edc\u5f00\u53d1", "url": "item?id=28181657", "create_at": "2021-08-15 00:13", "site_name": "hacknews"}]