[{"id": 39725, "hacknewsid": 31029101, "title": "90DaysOfDevOps", "title_zh": "", "url": "https://github.com/MichaelCade/90DaysOfDevOps", "create_at": "2022-04-15 00:25", "site_name": "hacknews"}, {"id": 39726, "hacknewsid": 31028943, "title": "Docker Desktop Extensions Preview", "title_zh": "", "url": "https://www.docker.com/blog/docker-extensions-preview/", "create_at": "2022-04-15 00:25", "site_name": "hacknews"}, {"id": 39727, "hacknewsid": 31028898, "title": "NTRU \u2013 open-source public-key lattice-based cryptography", "title_zh": "", "url": "https://en.wikipedia.org/wiki/NTRU", "create_at": "2022-04-15 00:25", "site_name": "hacknews"}, {"id": 39728, "hacknewsid": 31028815, "title": "I read 300 self-improvement books to learn these 3 lessons", "title_zh": "", "url": "https://www.youtube.com/watch?v=dndxT20s_pc", "create_at": "2022-04-15 00:25", "site_name": "hacknews"}, {"id": 39729, "hacknewsid": 31028722, "title": "Damn vulnerable web application (dvwa)", "title_zh": "", "url": "https://github.com/digininja/DVWA", "create_at": "2022-04-15 00:25", "site_name": "hacknews"}, {"id": 39730, "hacknewsid": 31028718, "title": "Spotify's Podcast Search Explained", "title_zh": "", "url": "https://www.pinecone.io/learn/spotify-podcast-search/", "create_at": "2022-04-15 00:25", "site_name": "hacknews"}, {"id": 39731, "hacknewsid": 31028594, "title": "Surveying SQL parser libraries in a few high-level languages", "title_zh": "", "url": "https://datastation.multiprocess.io/blog/2022-04-11-sql-parsers.html", "create_at": "2022-04-15 00:25", "site_name": "hacknews"}, {"id": 39732, "hacknewsid": 31028538, "title": "Hyperlocal Software: How Web3 opens new opportunities in software development", "title_zh": "", "url": "https://nickconfrey.medium.com/hyperlocal-software-164e94edb753", "create_at": "2022-04-15 00:25", "site_name": "hacknews"}, {"id": 39733, "hacknewsid": 31028490, "title": "Europe\u2019s first multilingual, generalizable AI model", "title_zh": "", "url": "https://docs.aleph-alpha.com/", "create_at": "2022-04-15 00:25", "site_name": "hacknews"}, {"id": 39734, "hacknewsid": 31028465, "title": "A Summary of the 80486 Opcodes and Instructions (1999)", "title_zh": "", "url": "https://gist.github.com/djmott/e3021055697f074af62bf0c9bbc77af2", "create_at": "2022-04-15 00:25", "site_name": "hacknews"}, {"id": 39735, "hacknewsid": 31028360, "title": "Edge of Emulation: Game Boy Sewing Machines", "title_zh": "", "url": "https://shonumi.github.io/articles/art22.html", "create_at": "2022-04-15 00:25", "site_name": "hacknews"}, {"id": 39736, "hacknewsid": 31028341, "title": "Set Up a Terraform Pipeline with GitHub Actions and GitHub OIDC for AWS", "title_zh": "", "url": "https://blog.symops.com/2022/04/14/terraform-pipeline-with-github-actions-and-github-oidc-for-aws/", "create_at": "2022-04-15 00:25", "site_name": "hacknews"}, {"id": 39737, "hacknewsid": 31028265, "title": "Researchers Gain New Understanding from Simple AI", "title_zh": "", "url": "https://www.quantamagazine.org/researchers-glimpse-how-ai-gets-so-good-at-language-processing-20220414/", "create_at": "2022-04-15 00:25", "site_name": "hacknews"}, {"id": 39738, "hacknewsid": 31028185, "title": "DocSearch: Search made for documentation \u2013 DocSearch by Algolia", "title_zh": "", "url": "https://docsearch.algolia.com/", "create_at": "2022-04-15 00:25", "site_name": "hacknews"}, {"id": 39739, "hacknewsid": 31028137, "title": "Vuenique: Low-level data visualization chart components for Vue developers", "title_zh": "", "url": "https://vuenique.net/", "create_at": "2022-04-15 00:25", "site_name": "hacknews"}]